{
  "_class": "group",
  "do_objectID": "AE630D59-5824-455C-ABA5-458CD99DDC45",
  "exportOptions": {
    "_class": "exportOptions",
    "do_objectID": "54E637FC-C254-4DE7-B8E6-854F6EC83E11",
    "exportFormats": [
    ],
    "includedLayerIds": [
    ],
    "layerOptions": 0,
    "shouldTrim": false
  },
  "frame": {
    "_class": "rect",
    "constrainProportions": false,
    "do_objectID": "52F73E94-72D5-4120-8FAF-F73213B937E6",
    "height": 307,
    "width": 447,
    "x": 0,
    "y": 0
  },
  "hasClickThrough": false,
  "isFlippedHorizontal": false,
  "isFlippedVertical": false,
  "isLocked": false,
  "isVisible": true,
  "layerListExpandedType": 0,
  "layers": [
    {
      "class": "group",
      "id": "E5F6C77E-E45A-4A1F-B16C-493C0777F400"
    },
    {
      "class": "shapeGroup",
      "id": "11B43712-2FFB-4A27-984D-63283FF303E9"
    },
    {
      "class": "text",
      "id": "A7FCB51C-6E87-4789-B6D8-A60341DBF79C"
    },
    {
      "class": "symbolInstance",
      "id": "505B715F-5361-44CA-AE87-28EBC0A33093"
    },
    {
      "class": "text",
      "id": "B6E8CC16-01AA-4B72-9785-E72E4A7CD5EC"
    },
    {
      "class": "text",
      "id": "758AFBEC-D549-4B08-A522-6B92642DDFB5"
    }
  ],
  "name": "Flyout",
  "nameIsFixed": true,
  "resizingConstraint": 63,
  "resizingType": 0,
  "rotation": 0,
  "shouldBreakMaskChain": false,
  "style": {
    "_class": "style",
    "do_objectID": "ED0F9A0C-2BCB-4967-9E82-F78737A0E93E",
    "endDecorationType": 0,
    "miterLimit": 10,
    "startDecorationType": 0
  }
}