{
  "_class": "shapePath",
  "booleanOperation": -1,
  "do_objectID": "A63023B0-2CD1-4ACA-A539-DA98AF313896",
  "edited": true,
  "exportOptions": {
    "_class": "exportOptions",
    "do_objectID": "36EBDF4B-BBD4-42BA-9043-3E88D045F74E",
    "exportFormats": [
    ],
    "includedLayerIds": [
    ],
    "layerOptions": 0,
    "shouldTrim": false
  },
  "frame": {
    "_class": "rect",
    "constrainProportions": false,
    "do_objectID": "318D282A-CFE8-40E5-8DDA-DA573829E49A",
    "height": 7,
    "width": 16,
    "x": 2,
    "y": 2
  },
  "isClosed": true,
  "isFlippedHorizontal": false,
  "isFlippedVertical": false,
  "isLocked": false,
  "isVisible": true,
  "layerListExpandedType": 0,
  "name": "Path",
  "nameIsFixed": false,
  "path": {
    "_class": "path",
    "isClosed": true,
    "pointRadiusBehaviour": 0,
    "points": [
      {
        "_class": "curvePoint",
        "cornerRadius": 0,
        "curveFrom": "{1, 0.2857142857142857}",
        "curveMode": 1,
        "curveTo": "{1, 0.2857142857142857}",
        "hasCurveFrom": false,
        "hasCurveTo": false,
        "point": "{1, 0.2857142857142857}"
      },
      {
        "_class": "curvePoint",
        "cornerRadius": 0,
        "curveFrom": "{0.5, 1}",
        "curveMode": 1,
        "curveTo": "{0.5, 1}",
        "hasCurveFrom": false,
        "hasCurveTo": false,
        "point": "{0.5, 1}"
      },
      {
        "_class": "curvePoint",
        "cornerRadius": 0,
        "curveFrom": "{0, 0.2857142857142857}",
        "curveMode": 1,
        "curveTo": "{0, 0.2857142857142857}",
        "hasCurveFrom": false,
        "hasCurveTo": false,
        "point": "{0, 0.2857142857142857}"
      },
      {
        "_class": "curvePoint",
        "cornerRadius": 0,
        "curveFrom": "{0, 0}",
        "curveMode": 1,
        "curveTo": "{0, 0}",
        "hasCurveFrom": false,
        "hasCurveTo": false,
        "point": "{0, 0}"
      },
      {
        "_class": "curvePoint",
        "cornerRadius": 0,
        "curveFrom": "{0.5, 0.7142857142857143}",
        "curveMode": 1,
        "curveTo": "{0.5, 0.7142857142857143}",
        "hasCurveFrom": false,
        "hasCurveTo": false,
        "point": "{0.5, 0.7142857142857143}"
      },
      {
        "_class": "curvePoint",
        "cornerRadius": 0,
        "curveFrom": "{1, 0}",
        "curveMode": 1,
        "curveTo": "{1, 0}",
        "hasCurveFrom": false,
        "hasCurveTo": false,
        "point": "{1, 0}"
      },
      {
        "_class": "curvePoint",
        "cornerRadius": 0,
        "curveFrom": "{1, 0.2857142857142857}",
        "curveMode": 1,
        "curveTo": "{1, 0.2857142857142857}",
        "hasCurveFrom": false,
        "hasCurveTo": false,
        "point": "{1, 0.2857142857142857}"
      }
    ]
  },
  "pointRadiusBehaviour": 0,
  "points": [
    {
      "_class": "curvePoint",
      "cornerRadius": 0,
      "curveFrom": "{1, 0.2857142857142857}",
      "curveMode": 1,
      "curveTo": "{1, 0.2857142857142857}",
      "hasCurveFrom": false,
      "hasCurveTo": false,
      "point": "{1, 0.2857142857142857}"
    },
    {
      "_class": "curvePoint",
      "cornerRadius": 0,
      "curveFrom": "{0.5, 1}",
      "curveMode": 1,
      "curveTo": "{0.5, 1}",
      "hasCurveFrom": false,
      "hasCurveTo": false,
      "point": "{0.5, 1}"
    },
    {
      "_class": "curvePoint",
      "cornerRadius": 0,
      "curveFrom": "{0, 0.2857142857142857}",
      "curveMode": 1,
      "curveTo": "{0, 0.2857142857142857}",
      "hasCurveFrom": false,
      "hasCurveTo": false,
      "point": "{0, 0.2857142857142857}"
    },
    {
      "_class": "curvePoint",
      "cornerRadius": 0,
      "curveFrom": "{0, 0}",
      "curveMode": 1,
      "curveTo": "{0, 0}",
      "hasCurveFrom": false,
      "hasCurveTo": false,
      "point": "{0, 0}"
    },
    {
      "_class": "curvePoint",
      "cornerRadius": 0,
      "curveFrom": "{0.5, 0.7142857142857143}",
      "curveMode": 1,
      "curveTo": "{0.5, 0.7142857142857143}",
      "hasCurveFrom": false,
      "hasCurveTo": false,
      "point": "{0.5, 0.7142857142857143}"
    },
    {
      "_class": "curvePoint",
      "cornerRadius": 0,
      "curveFrom": "{1, 0}",
      "curveMode": 1,
      "curveTo": "{1, 0}",
      "hasCurveFrom": false,
      "hasCurveTo": false,
      "point": "{1, 0}"
    },
    {
      "_class": "curvePoint",
      "cornerRadius": 0,
      "curveFrom": "{1, 0.2857142857142857}",
      "curveMode": 1,
      "curveTo": "{1, 0.2857142857142857}",
      "hasCurveFrom": false,
      "hasCurveTo": false,
      "point": "{1, 0.2857142857142857}"
    }
  ],
  "resizingConstraint": 63,
  "resizingType": 0,
  "rotation": 0,
  "shouldBreakMaskChain": false
}