{
  "_class": "shapePath",
  "booleanOperation": -1,
  "do_objectID": "0F7BE00B-C9FC-4DAF-9BE3-79D86268EB3A",
  "edited": true,
  "exportOptions": {
    "_class": "exportOptions",
    "do_objectID": "88819135-E403-47CD-BC7D-0DA4E0E0955F",
    "exportFormats": [
    ],
    "includedLayerIds": [
    ],
    "layerOptions": 0,
    "shouldTrim": false
  },
  "frame": {
    "_class": "rect",
    "constrainProportions": false,
    "do_objectID": "988BC4CC-ABED-46B0-91A2-4FC712C92E60",
    "height": 10.09,
    "width": 9,
    "x": 1.5,
    "y": 0
  },
  "isClosed": true,
  "isFlippedHorizontal": false,
  "isFlippedVertical": false,
  "isLocked": false,
  "isVisible": true,
  "layerListExpandedType": 0,
  "name": "Path",
  "nameIsFixed": false,
  "path": {
    "_class": "path",
    "isClosed": true,
    "pointRadiusBehaviour": 0,
    "points": [
      {
        "_class": "curvePoint",
        "cornerRadius": 0,
        "curveFrom": "{0.3888888888888889, 0}",
        "curveMode": 1,
        "curveTo": "{0.3888888888888889, 0}",
        "hasCurveFrom": false,
        "hasCurveTo": false,
        "point": "{0.3888888888888889, 0}"
      },
      {
        "_class": "curvePoint",
        "cornerRadius": 0,
        "curveFrom": "{0.3888888888888889, 0.554013875123885}",
        "curveMode": 1,
        "curveTo": "{0.3888888888888889, 0.554013875123885}",
        "hasCurveFrom": false,
        "hasCurveTo": false,
        "point": "{0.3888888888888889, 0.554013875123885}"
      },
      {
        "_class": "curvePoint",
        "cornerRadius": 0,
        "curveFrom": "{0, 0.554013875123885}",
        "curveMode": 1,
        "curveTo": "{0, 0.554013875123885}",
        "hasCurveFrom": false,
        "hasCurveTo": false,
        "point": "{0, 0.554013875123885}"
      },
      {
        "_class": "curvePoint",
        "cornerRadius": 0,
        "curveFrom": "{0.5, 1}",
        "curveMode": 1,
        "curveTo": "{0.5, 1}",
        "hasCurveFrom": false,
        "hasCurveTo": false,
        "point": "{0.5, 1}"
      },
      {
        "_class": "curvePoint",
        "cornerRadius": 0,
        "curveFrom": "{1, 0.554013875123885}",
        "curveMode": 1,
        "curveTo": "{1, 0.554013875123885}",
        "hasCurveFrom": false,
        "hasCurveTo": false,
        "point": "{1, 0.554013875123885}"
      },
      {
        "_class": "curvePoint",
        "cornerRadius": 0,
        "curveFrom": "{0.61111111111111116, 0.554013875123885}",
        "curveMode": 1,
        "curveTo": "{0.61111111111111116, 0.554013875123885}",
        "hasCurveFrom": false,
        "hasCurveTo": false,
        "point": "{0.61111111111111116, 0.554013875123885}"
      },
      {
        "_class": "curvePoint",
        "cornerRadius": 0,
        "curveFrom": "{0.61111111111111116, 0}",
        "curveMode": 1,
        "curveTo": "{0.61111111111111116, 0}",
        "hasCurveFrom": false,
        "hasCurveTo": false,
        "point": "{0.61111111111111116, 0}"
      },
      {
        "_class": "curvePoint",
        "cornerRadius": 0,
        "curveFrom": "{0.3888888888888889, 0}",
        "curveMode": 1,
        "curveTo": "{0.3888888888888889, 0}",
        "hasCurveFrom": false,
        "hasCurveTo": false,
        "point": "{0.3888888888888889, 0}"
      }
    ]
  },
  "pointRadiusBehaviour": 0,
  "points": [
    {
      "_class": "curvePoint",
      "cornerRadius": 0,
      "curveFrom": "{0.3888888888888889, 0}",
      "curveMode": 1,
      "curveTo": "{0.3888888888888889, 0}",
      "hasCurveFrom": false,
      "hasCurveTo": false,
      "point": "{0.3888888888888889, 0}"
    },
    {
      "_class": "curvePoint",
      "cornerRadius": 0,
      "curveFrom": "{0.3888888888888889, 0.554013875123885}",
      "curveMode": 1,
      "curveTo": "{0.3888888888888889, 0.554013875123885}",
      "hasCurveFrom": false,
      "hasCurveTo": false,
      "point": "{0.3888888888888889, 0.554013875123885}"
    },
    {
      "_class": "curvePoint",
      "cornerRadius": 0,
      "curveFrom": "{0, 0.554013875123885}",
      "curveMode": 1,
      "curveTo": "{0, 0.554013875123885}",
      "hasCurveFrom": false,
      "hasCurveTo": false,
      "point": "{0, 0.554013875123885}"
    },
    {
      "_class": "curvePoint",
      "cornerRadius": 0,
      "curveFrom": "{0.5, 1}",
      "curveMode": 1,
      "curveTo": "{0.5, 1}",
      "hasCurveFrom": false,
      "hasCurveTo": false,
      "point": "{0.5, 1}"
    },
    {
      "_class": "curvePoint",
      "cornerRadius": 0,
      "curveFrom": "{1, 0.554013875123885}",
      "curveMode": 1,
      "curveTo": "{1, 0.554013875123885}",
      "hasCurveFrom": false,
      "hasCurveTo": false,
      "point": "{1, 0.554013875123885}"
    },
    {
      "_class": "curvePoint",
      "cornerRadius": 0,
      "curveFrom": "{0.61111111111111116, 0.554013875123885}",
      "curveMode": 1,
      "curveTo": "{0.61111111111111116, 0.554013875123885}",
      "hasCurveFrom": false,
      "hasCurveTo": false,
      "point": "{0.61111111111111116, 0.554013875123885}"
    },
    {
      "_class": "curvePoint",
      "cornerRadius": 0,
      "curveFrom": "{0.61111111111111116, 0}",
      "curveMode": 1,
      "curveTo": "{0.61111111111111116, 0}",
      "hasCurveFrom": false,
      "hasCurveTo": false,
      "point": "{0.61111111111111116, 0}"
    },
    {
      "_class": "curvePoint",
      "cornerRadius": 0,
      "curveFrom": "{0.3888888888888889, 0}",
      "curveMode": 1,
      "curveTo": "{0.3888888888888889, 0}",
      "hasCurveFrom": false,
      "hasCurveTo": false,
      "point": "{0.3888888888888889, 0}"
    }
  ],
  "resizingConstraint": 63,
  "resizingType": 0,
  "rotation": 0,
  "shouldBreakMaskChain": false
}