{
  "_class": "shapeGroup",
  "clippingMaskMode": 0,
  "do_objectID": "380ACCB3-9343-4528-B6B2-7B1C9E0D25CB",
  "exportOptions": {
    "_class": "exportOptions",
    "do_objectID": "C3D57900-D1EA-4673-9DBD-94BF9B9B996C",
    "exportFormats": [
    ],
    "includedLayerIds": [
    ],
    "layerOptions": 0,
    "shouldTrim": false
  },
  "frame": {
    "_class": "rect",
    "constrainProportions": true,
    "do_objectID": "840E0EDE-2F59-4B22-BEAB-7D1E04F096C2",
    "height": 10.41,
    "width": 18.00000000000004,
    "x": 3.000000000000007,
    "y": 7
  },
  "hasClickThrough": false,
  "hasClippingMask": false,
  "isFlippedHorizontal": false,
  "isFlippedVertical": false,
  "isLocked": false,
  "isVisible": true,
  "layerListExpandedType": 0,
  "layers": [
    {
      "class": "shapePath",
      "id": "13C1938A-E48D-49AD-891E-BE428E320A3A"
    }
  ],
  "name": "Icon",
  "nameIsFixed": false,
  "resizingConstraint": 63,
  "resizingType": 0,
  "rotation": 0,
  "shouldBreakMaskChain": false,
  "style": {
    "_class": "style",
    "do_objectID": "88E1C54C-B28C-4F51-BAED-7928AD62EC23",
    "endDecorationType": 0,
    "fills": [
      {
        "_class": "fill",
        "color": {
          "_class": "color",
          "alpha": 1,
          "blue": 0,
          "green": 0,
          "red": 0
        },
        "fillType": 0,
        "isEnabled": true,
        "noiseIndex": 0,
        "noiseIntensity": 0,
        "patternFillType": 0,
        "patternTileScale": 1
      }
    ],
    "miterLimit": 10,
    "startDecorationType": 0
  },
  "windingRule": 1
}