{
  "_class": "shapeGroup",
  "clippingMaskMode": 0,
  "do_objectID": "2F970AE6-C71B-4629-9D3B-B78C184E94DE",
  "exportOptions": {
    "_class": "exportOptions",
    "do_objectID": "99518C53-0246-4291-BAD0-00BABAA0F671",
    "exportFormats": [
    ],
    "includedLayerIds": [
    ],
    "layerOptions": 0,
    "shouldTrim": false
  },
  "frame": {
    "_class": "rect",
    "constrainProportions": false,
    "do_objectID": "D3D7C143-FD53-4442-9B68-BC67B618AFBA",
    "height": 24,
    "width": 24.00000000000006,
    "x": 0,
    "y": 0
  },
  "hasClickThrough": false,
  "hasClippingMask": false,
  "isFlippedHorizontal": false,
  "isFlippedVertical": false,
  "isLocked": false,
  "isVisible": true,
  "layerListExpandedType": 0,
  "layers": [
    {
      "class": "shapePath",
      "id": "08737B7A-224C-43AB-9510-5287A56B9139"
    }
  ],
  "name": "Bounds",
  "nameIsFixed": true,
  "resizingConstraint": 63,
  "resizingType": 0,
  "rotation": 0,
  "shouldBreakMaskChain": false,
  "style": {
    "_class": "style",
    "do_objectID": "4A0E857D-7979-41E3-8315-23ABF1C8400D",
    "endDecorationType": 0,
    "miterLimit": 10,
    "startDecorationType": 0
  },
  "windingRule": 1
}