{
  "_class": "shapePath",
  "booleanOperation": -1,
  "do_objectID": "3FDD243B-D7BF-4BF3-ADC0-D0D34BAB232C",
  "edited": true,
  "exportOptions": {
    "_class": "exportOptions",
    "do_objectID": "74BA1444-2066-466A-9B76-E6C2CC7F99F9",
    "exportFormats": [
    ],
    "includedLayerIds": [
    ],
    "layerOptions": 0,
    "shouldTrim": false
  },
  "frame": {
    "_class": "rect",
    "constrainProportions": false,
    "do_objectID": "82442DDD-CB9A-4672-9492-A206E9C358A8",
    "height": 12,
    "width": 18,
    "x": 0,
    "y": 0
  },
  "isClosed": true,
  "isFlippedHorizontal": false,
  "isFlippedVertical": false,
  "isLocked": false,
  "isVisible": true,
  "layerListExpandedType": 0,
  "name": "Path",
  "nameIsFixed": false,
  "path": {
    "_class": "path",
    "isClosed": true,
    "pointRadiusBehaviour": 0,
    "points": [
      {
        "_class": "curvePoint",
        "cornerRadius": 0,
        "curveFrom": "{1, 0.41666666666666669}",
        "curveMode": 1,
        "curveTo": "{1, 0.41666666666666669}",
        "hasCurveFrom": false,
        "hasCurveTo": false,
        "point": "{1, 0.41666666666666669}"
      },
      {
        "_class": "curvePoint",
        "cornerRadius": 0,
        "curveFrom": "{0.21277777777777779, 0.41666666666666669}",
        "curveMode": 1,
        "curveTo": "{0.21277777777777779, 0.41666666666666669}",
        "hasCurveFrom": false,
        "hasCurveTo": false,
        "point": "{0.21277777777777779, 0.41666666666666669}"
      },
      {
        "_class": "curvePoint",
        "cornerRadius": 0,
        "curveFrom": "{0.41166666666666668, 0.11750000000000001}",
        "curveMode": 1,
        "curveTo": "{0.41166666666666668, 0.11750000000000001}",
        "hasCurveFrom": false,
        "hasCurveTo": false,
        "point": "{0.41166666666666668, 0.11750000000000001}"
      },
      {
        "_class": "curvePoint",
        "cornerRadius": 0,
        "curveFrom": "{0.33333333333333331, 0}",
        "curveMode": 1,
        "curveTo": "{0.33333333333333331, 0}",
        "hasCurveFrom": false,
        "hasCurveTo": false,
        "point": "{0.33333333333333331, 0}"
      },
      {
        "_class": "curvePoint",
        "cornerRadius": 0,
        "curveFrom": "{0, 0.5}",
        "curveMode": 1,
        "curveTo": "{0, 0.5}",
        "hasCurveFrom": false,
        "hasCurveTo": false,
        "point": "{0, 0.5}"
      },
      {
        "_class": "curvePoint",
        "cornerRadius": 0,
        "curveFrom": "{0.33333333333333331, 1}",
        "curveMode": 1,
        "curveTo": "{0.33333333333333331, 1}",
        "hasCurveFrom": false,
        "hasCurveTo": false,
        "point": "{0.33333333333333331, 1}"
      },
      {
        "_class": "curvePoint",
        "cornerRadius": 0,
        "curveFrom": "{0.41166666666666668, 0.88249999999999995}",
        "curveMode": 1,
        "curveTo": "{0.41166666666666668, 0.88249999999999995}",
        "hasCurveFrom": false,
        "hasCurveTo": false,
        "point": "{0.41166666666666668, 0.88249999999999995}"
      },
      {
        "_class": "curvePoint",
        "cornerRadius": 0,
        "curveFrom": "{0.21277777777777779, 0.58333333333333337}",
        "curveMode": 1,
        "curveTo": "{0.21277777777777779, 0.58333333333333337}",
        "hasCurveFrom": false,
        "hasCurveTo": false,
        "point": "{0.21277777777777779, 0.58333333333333337}"
      },
      {
        "_class": "curvePoint",
        "cornerRadius": 0,
        "curveFrom": "{1, 0.58333333333333337}",
        "curveMode": 1,
        "curveTo": "{1, 0.58333333333333337}",
        "hasCurveFrom": false,
        "hasCurveTo": false,
        "point": "{1, 0.58333333333333337}"
      }
    ]
  },
  "pointRadiusBehaviour": 0,
  "points": [
    {
      "_class": "curvePoint",
      "cornerRadius": 0,
      "curveFrom": "{1, 0.41666666666666669}",
      "curveMode": 1,
      "curveTo": "{1, 0.41666666666666669}",
      "hasCurveFrom": false,
      "hasCurveTo": false,
      "point": "{1, 0.41666666666666669}"
    },
    {
      "_class": "curvePoint",
      "cornerRadius": 0,
      "curveFrom": "{0.21277777777777779, 0.41666666666666669}",
      "curveMode": 1,
      "curveTo": "{0.21277777777777779, 0.41666666666666669}",
      "hasCurveFrom": false,
      "hasCurveTo": false,
      "point": "{0.21277777777777779, 0.41666666666666669}"
    },
    {
      "_class": "curvePoint",
      "cornerRadius": 0,
      "curveFrom": "{0.41166666666666668, 0.11750000000000001}",
      "curveMode": 1,
      "curveTo": "{0.41166666666666668, 0.11750000000000001}",
      "hasCurveFrom": false,
      "hasCurveTo": false,
      "point": "{0.41166666666666668, 0.11750000000000001}"
    },
    {
      "_class": "curvePoint",
      "cornerRadius": 0,
      "curveFrom": "{0.33333333333333331, 0}",
      "curveMode": 1,
      "curveTo": "{0.33333333333333331, 0}",
      "hasCurveFrom": false,
      "hasCurveTo": false,
      "point": "{0.33333333333333331, 0}"
    },
    {
      "_class": "curvePoint",
      "cornerRadius": 0,
      "curveFrom": "{0, 0.5}",
      "curveMode": 1,
      "curveTo": "{0, 0.5}",
      "hasCurveFrom": false,
      "hasCurveTo": false,
      "point": "{0, 0.5}"
    },
    {
      "_class": "curvePoint",
      "cornerRadius": 0,
      "curveFrom": "{0.33333333333333331, 1}",
      "curveMode": 1,
      "curveTo": "{0.33333333333333331, 1}",
      "hasCurveFrom": false,
      "hasCurveTo": false,
      "point": "{0.33333333333333331, 1}"
    },
    {
      "_class": "curvePoint",
      "cornerRadius": 0,
      "curveFrom": "{0.41166666666666668, 0.88249999999999995}",
      "curveMode": 1,
      "curveTo": "{0.41166666666666668, 0.88249999999999995}",
      "hasCurveFrom": false,
      "hasCurveTo": false,
      "point": "{0.41166666666666668, 0.88249999999999995}"
    },
    {
      "_class": "curvePoint",
      "cornerRadius": 0,
      "curveFrom": "{0.21277777777777779, 0.58333333333333337}",
      "curveMode": 1,
      "curveTo": "{0.21277777777777779, 0.58333333333333337}",
      "hasCurveFrom": false,
      "hasCurveTo": false,
      "point": "{0.21277777777777779, 0.58333333333333337}"
    },
    {
      "_class": "curvePoint",
      "cornerRadius": 0,
      "curveFrom": "{1, 0.58333333333333337}",
      "curveMode": 1,
      "curveTo": "{1, 0.58333333333333337}",
      "hasCurveFrom": false,
      "hasCurveTo": false,
      "point": "{1, 0.58333333333333337}"
    }
  ],
  "resizingConstraint": 63,
  "resizingType": 0,
  "rotation": 0,
  "shouldBreakMaskChain": false
}