{
  "_class": "shapeGroup",
  "clippingMaskMode": 0,
  "do_objectID": "71CD8024-616A-4EEE-AE6F-4D8A23607AD5",
  "exportOptions": {
    "_class": "exportOptions",
    "do_objectID": "D8CA984A-1AF7-43DD-A317-D580896A0816",
    "exportFormats": [
    ],
    "includedLayerIds": [
    ],
    "layerOptions": 0,
    "shouldTrim": false
  },
  "frame": {
    "_class": "rect",
    "constrainProportions": true,
    "do_objectID": "E0354EEE-D30B-4012-9773-C3175738116C",
    "height": 18.0025,
    "width": 18.00126186740555,
    "x": 3,
    "y": 2.9975000000004
  },
  "hasClickThrough": false,
  "hasClippingMask": false,
  "isFlippedHorizontal": false,
  "isFlippedVertical": false,
  "isLocked": false,
  "isVisible": true,
  "layerListExpandedType": 0,
  "layers": [
    {
      "class": "shapePath",
      "id": "EA85FDF3-B478-4037-AF4C-AC9272FE481B"
    },
    {
      "class": "shapePath",
      "id": "515CDD5A-14E3-4C60-A25F-905902BC449A"
    }
  ],
  "name": "Icon",
  "nameIsFixed": false,
  "resizingConstraint": 63,
  "resizingType": 0,
  "rotation": 0,
  "shouldBreakMaskChain": false,
  "style": {
    "_class": "style",
    "do_objectID": "8F81EAEC-797C-490C-9D27-9E29C9D4720A",
    "endDecorationType": 0,
    "fills": [
      {
        "_class": "fill",
        "color": {
          "_class": "color",
          "alpha": 1,
          "blue": 0,
          "green": 0,
          "red": 0
        },
        "fillType": 0,
        "isEnabled": true,
        "noiseIndex": 0,
        "noiseIntensity": 0,
        "patternFillType": 0,
        "patternTileScale": 1
      }
    ],
    "miterLimit": 10,
    "startDecorationType": 0
  },
  "windingRule": 1
}