{
  "_class": "shapeGroup",
  "clippingMaskMode": 0,
  "do_objectID": "162EBE4A-A743-46A6-AE3B-823063630B15",
  "exportOptions": {
    "_class": "exportOptions",
    "do_objectID": "EE325414-AEDB-4213-99FB-B39DE9206927",
    "exportFormats": [
    ],
    "includedLayerIds": [
    ],
    "layerOptions": 0,
    "shouldTrim": false
  },
  "frame": {
    "_class": "rect",
    "constrainProportions": true,
    "do_objectID": "6470BFF7-D07D-4F0F-816F-0448DA3751FA",
    "height": 20,
    "width": 14,
    "x": 5,
    "y": 2
  },
  "hasClickThrough": false,
  "hasClippingMask": false,
  "isFlippedHorizontal": false,
  "isFlippedVertical": false,
  "isLocked": false,
  "isVisible": true,
  "layerListExpandedType": 0,
  "layers": [
    {
      "class": "shapePath",
      "id": "A017219A-DB1C-4CA6-A44B-49E6B869FC05"
    },
    {
      "class": "shapePath",
      "id": "B2EF0CFD-ED08-42EE-8905-8FCF2D3CEEFB"
    }
  ],
  "name": "Icon",
  "nameIsFixed": false,
  "resizingConstraint": 63,
  "resizingType": 0,
  "rotation": 0,
  "shouldBreakMaskChain": false,
  "style": {
    "_class": "style",
    "do_objectID": "D8EE5D58-BF9A-4EEF-B8EA-41ABEC86C184",
    "endDecorationType": 0,
    "fills": [
      {
        "_class": "fill",
        "color": {
          "_class": "color",
          "alpha": 1,
          "blue": 0,
          "green": 0,
          "red": 0
        },
        "fillType": 0,
        "isEnabled": true,
        "noiseIndex": 0,
        "noiseIntensity": 0,
        "patternFillType": 0,
        "patternTileScale": 1
      }
    ],
    "miterLimit": 10,
    "startDecorationType": 0
  },
  "windingRule": 1
}