{
  "_class": "shapeGroup",
  "clippingMaskMode": 0,
  "do_objectID": "3921D986-09F0-4EDA-886F-4778383BF473",
  "exportOptions": {
    "_class": "exportOptions",
    "do_objectID": "C238B638-EFC6-43DA-9ED3-EC76214EE1B5",
    "exportFormats": [
    ],
    "includedLayerIds": [
    ],
    "layerOptions": 0,
    "shouldTrim": false
  },
  "frame": {
    "_class": "rect",
    "constrainProportions": false,
    "do_objectID": "77C6A0EC-1491-4D68-9670-2D94BBE48EF2",
    "height": 24,
    "width": 24,
    "x": 0,
    "y": 0
  },
  "hasClickThrough": false,
  "hasClippingMask": false,
  "isFlippedHorizontal": false,
  "isFlippedVertical": false,
  "isLocked": false,
  "isVisible": true,
  "layerListExpandedType": 0,
  "layers": [
    {
      "class": "shapePath",
      "id": "BB57A0B0-8A6D-44A3-8CB0-1FBA24CF208C"
    }
  ],
  "name": "Bounds",
  "nameIsFixed": false,
  "resizingConstraint": 63,
  "resizingType": 0,
  "rotation": 0,
  "shouldBreakMaskChain": false,
  "style": {
    "_class": "style",
    "do_objectID": "D1BB63BE-77F2-419C-9E61-A620C0DDB8CB",
    "endDecorationType": 0,
    "miterLimit": 10,
    "startDecorationType": 0
  },
  "windingRule": 1
}