{
  "_class": "shapeGroup",
  "clippingMaskMode": 0,
  "do_objectID": "67B62C4D-7F4B-496C-A82A-408E80DD14F1",
  "exportOptions": {
    "_class": "exportOptions",
    "do_objectID": "72B29361-BD12-442B-9BD6-C0191C6D951E",
    "exportFormats": [
    ],
    "includedLayerIds": [
    ],
    "layerOptions": 0,
    "shouldTrim": false
  },
  "frame": {
    "_class": "rect",
    "constrainProportions": false,
    "do_objectID": "7EE27E0C-B371-4AE4-879F-4D4846B6F0C9",
    "height": 67,
    "width": 501,
    "x": 0,
    "y": 0
  },
  "hasClickThrough": false,
  "hasClippingMask": false,
  "isFlippedHorizontal": false,
  "isFlippedVertical": false,
  "isLocked": false,
  "isVisible": true,
  "layerListExpandedType": 0,
  "layers": [
    {
      "class": "rectangle",
      "id": "EA096AEB-A5CF-4A43-A797-3AE1D0AFFA7E"
    }
  ],
  "name": "Rectangle 28 Copy",
  "nameIsFixed": false,
  "resizingConstraint": 63,
  "resizingType": 0,
  "rotation": 0,
  "shouldBreakMaskChain": false,
  "style": {
    "_class": "style",
    "borders": [
      {
        "_class": "border",
        "color": {
          "_class": "color",
          "alpha": 1,
          "blue": 0.592,
          "green": 0.592,
          "red": 0.592
        },
        "fillType": 0,
        "isEnabled": false,
        "position": 1,
        "thickness": 1
      }
    ],
    "do_objectID": "2B5F711C-C5D7-478D-A45A-5BAA881B838F",
    "endDecorationType": 0,
    "fills": [
      {
        "_class": "fill",
        "color": {
          "_class": "color",
          "alpha": 1,
          "blue": 0.984313725490196,
          "green": 0.9568627450980391,
          "red": 0.8980392156862745
        },
        "fillType": 0,
        "isEnabled": true,
        "noiseIndex": 0,
        "noiseIntensity": 0,
        "patternFillType": 1,
        "patternTileScale": 1
      }
    ],
    "miterLimit": 10,
    "startDecorationType": 0
  },
  "windingRule": 1
}