{
  "_class": "shapeGroup",
  "clippingMaskMode": 0,
  "do_objectID": "09CF470F-B43C-471A-B9FF-32CBE63DAD7A",
  "exportOptions": {
    "_class": "exportOptions",
    "do_objectID": "8397BD6F-0593-44E0-81DA-DAA7FD0FCEC5",
    "exportFormats": [
    ],
    "includedLayerIds": [
    ],
    "layerOptions": 0,
    "shouldTrim": false
  },
  "frame": {
    "_class": "rect",
    "constrainProportions": false,
    "do_objectID": "D1DCB3E3-38A2-4F2F-A7E9-A020FE894BEC",
    "height": 24,
    "width": 24,
    "x": 0,
    "y": 0
  },
  "hasClickThrough": false,
  "hasClippingMask": false,
  "isFlippedHorizontal": false,
  "isFlippedVertical": false,
  "isLocked": false,
  "isVisible": true,
  "layerListExpandedType": 0,
  "layers": [
    {
      "class": "shapePath",
      "id": "3A407B56-94C5-4A5B-8435-21195BD765AE"
    }
  ],
  "name": "Bounds",
  "nameIsFixed": false,
  "resizingConstraint": 63,
  "resizingType": 0,
  "rotation": 0,
  "shouldBreakMaskChain": false,
  "style": {
    "_class": "style",
    "do_objectID": "22548C87-28A1-410E-99A8-C95950A20CE4",
    "endDecorationType": 0,
    "miterLimit": 10,
    "startDecorationType": 0
  },
  "windingRule": 1
}