{
  "_class": "shapeGroup",
  "clippingMaskMode": 0,
  "do_objectID": "06A9EFCE-27AB-434B-91AB-588A7DE752DE",
  "exportOptions": {
    "_class": "exportOptions",
    "do_objectID": "7A2D5C45-0127-42E3-848B-7CEAEC2BA2B3",
    "exportFormats": [
    ],
    "includedLayerIds": [
    ],
    "layerOptions": 0,
    "shouldTrim": false
  },
  "frame": {
    "_class": "rect",
    "constrainProportions": false,
    "do_objectID": "81DA9FFC-B410-44E0-85DB-639E80B64184",
    "height": 24,
    "width": 24,
    "x": 0,
    "y": 0
  },
  "hasClickThrough": false,
  "hasClippingMask": false,
  "isFlippedHorizontal": false,
  "isFlippedVertical": false,
  "isLocked": false,
  "isVisible": true,
  "layerListExpandedType": 0,
  "layers": [
    {
      "class": "shapePath",
      "id": "6F3C0C4A-23D3-49DD-B54D-DF57BAF2AF38"
    }
  ],
  "name": "Bounds",
  "nameIsFixed": true,
  "resizingConstraint": 63,
  "resizingType": 0,
  "rotation": 0,
  "shouldBreakMaskChain": false,
  "style": {
    "_class": "style",
    "do_objectID": "BB89CCCA-4C57-452A-A39A-F4276E5CD339",
    "endDecorationType": 0,
    "miterLimit": 10,
    "startDecorationType": 0
  },
  "windingRule": 1
}