{
  "_class": "shapeGroup",
  "clippingMaskMode": 0,
  "do_objectID": "40AC3880-3281-4686-B8CA-8B6D0E5828CB",
  "exportOptions": {
    "_class": "exportOptions",
    "do_objectID": "3CC6ED8F-5FBC-4B6F-A738-907E13F998CC",
    "exportFormats": [
      {
        "_class": "exportFormat",
        "absoluteSize": 0,
        "fileFormat": "pdf",
        "name": "",
        "namingScheme": 0,
        "scale": 1,
        "visibleScaleType": 0
      }
    ],
    "includedLayerIds": [
    ],
    "layerOptions": 0,
    "shouldTrim": false
  },
  "frame": {
    "_class": "rect",
    "constrainProportions": false,
    "do_objectID": "D143A8C5-80E9-4497-B201-EA207FBC823A",
    "height": 40,
    "width": 142,
    "x": 0,
    "y": 0
  },
  "hasClickThrough": false,
  "hasClippingMask": false,
  "isFlippedHorizontal": false,
  "isFlippedVertical": false,
  "isLocked": false,
  "isVisible": true,
  "layerListExpandedType": 0,
  "layers": [
    {
      "class": "rectangle",
      "id": "CB396F60-3067-43E2-8985-8ED86AEA42DF"
    }
  ],
  "name": "Rectangle 2 Copy",
  "nameIsFixed": false,
  "originalObjectID": "60FFF5AD-417B-45F3-9679-5ABDBD3252B9",
  "resizingConstraint": 63,
  "resizingType": 0,
  "rotation": 0,
  "shouldBreakMaskChain": false,
  "style": {
    "_class": "style",
    "borders": [
      {
        "_class": "border",
        "color": {
          "_class": "color",
          "alpha": 1,
          "blue": 0.8549019607843137,
          "green": 0.5647058823529416,
          "red": 0
        },
        "fillType": 0,
        "isEnabled": false,
        "position": 1,
        "thickness": 1
      }
    ],
    "do_objectID": "FCCA71B2-BF4D-4D30-9244-97D18D3D6A39",
    "endDecorationType": 0,
    "fills": [
      {
        "_class": "fill",
        "color": {
          "_class": "color",
          "alpha": 1,
          "blue": 1,
          "green": 1,
          "red": 1
        },
        "fillType": 0,
        "isEnabled": true,
        "noiseIndex": 0,
        "noiseIntensity": 0,
        "patternFillType": 1,
        "patternTileScale": 1
      }
    ],
    "miterLimit": 10,
    "startDecorationType": 0
  },
  "windingRule": 1
}